input_num/__init__.py
input_num-1.1.5.dist-info/LICENSE
input_num-1.1.5.dist-info/METADATA
input_num-1.1.5.dist-info/WHEEL
input_num-1.1.5.dist-info/top_level.txt
input_num-1.1.5.dist-info/RECORD
