Metadata-Version: 2.1
Name: input-num
Version: 1.1.5
Summary: Python package - input_num is like input but it only accepts numbers
Home-page: https://github.com/HexagonCore/input_num
Author: Hexagon Core Development
Author-email: mp3martin.developer@gmail.com
License: MIT
Platform: UNKNOWN
License-File: LICENSE
Requires-Dist: markdown
Requires-Dist: requests
